protoflow/__init__.py
protoflow/applications/__init__.py
protoflow/applications/deeplvq.py
protoflow/applications/glvq.py
protoflow/applications/gmlvq.py
protoflow/applications/knn.py
protoflow/applications/lvq1.py
protoflow/applications/lvqmln.py
protoflow/applications/network.py
protoflow/callbacks/__init__.py
protoflow/callbacks/callbacks.py
protoflow/datasets/__init__.py
protoflow/datasets/tecator.py
protoflow/experimental/__init__.py
protoflow/experimental/applications/__init__.py
protoflow/experimental/callbacks/__init__.py
protoflow/experimental/callbacks/callbacks.py
protoflow/experimental/functions/__init__.py
protoflow/experimental/functions/initializers.py
protoflow/experimental/layers/__init__.py
protoflow/experimental/modules/__init__.py
protoflow/experimental/modules/losses.py
protoflow/experimental/modules/metrics.py
protoflow/experimental/utils/__init__.py
protoflow/experimental/utils/utils.py
protoflow/functions/__init__.py
protoflow/functions/activations.py
protoflow/functions/distances.py
protoflow/functions/linalg.py
protoflow/functions/normalization.py
protoflow/functions/products.py
protoflow/layers/__init__.py
protoflow/layers/competitions.py
protoflow/layers/distances.py
protoflow/layers/products.py
protoflow/layers/projections.py
protoflow/layers/prototypes.py
protoflow/modules/__init__.py
protoflow/modules/constraints.py
protoflow/modules/initializers.py
protoflow/modules/losses.py
protoflow/modules/metrics.py
protoflow/modules/regularizers.py
protoflow/utils/__init__.py
protoflow/utils/celluloid.py
protoflow/utils/colors.py
protoflow/utils/confusion_matrix.py
protoflow/utils/data.py
protoflow/utils/utils.py
tests/__init__.py
tests/test_applications.py
tests/test_datasets.py
tests/test_functions.py
tests/test_layers.py
tests/test_modules.py
tests/test_utils.py
protoflow-0.2.1.dist-info/LICENSE
protoflow-0.2.1.dist-info/METADATA
protoflow-0.2.1.dist-info/WHEEL
protoflow-0.2.1.dist-info/top_level.txt
protoflow-0.2.1.dist-info/RECORD
