Metadata-Version: 2.1
Name: protoflow
Version: 0.2.1
Summary: Highly extensible, GPU-supported Learning Vector Quantization (LVQ) toolbox built using Tensorflow 2.x and its Keras API.
Home-page: https://github.com/si-cim/protoflow
Author: Jensun Ravichandran
Author-email: jjensun@gmail.com
License: MIT
Download-URL: https://github.com/si-cim/protoflow.git
Platform: UNKNOWN
Classifier: Development Status :: 2 - Pre-Alpha
Classifier: Environment :: Console
Classifier: Intended Audience :: Developers
Classifier: Intended Audience :: Education
Classifier: Intended Audience :: Science/Research
Classifier: License :: OSI Approved :: MIT License
Classifier: Programming Language :: Python :: 3.6
Classifier: Programming Language :: Python :: 3.7
Classifier: Programming Language :: Python :: 3.8
Classifier: Operating System :: OS Independent
Classifier: Topic :: Scientific/Engineering :: Artificial Intelligence
Classifier: Topic :: Software Development :: Libraries
Classifier: Topic :: Software Development :: Libraries :: Python Modules
Requires-Dist: tensorflow (>=2.2.0)
Requires-Dist: numpy (>=1.9.1)
Requires-Dist: sklearn
Provides-Extra: docs
Requires-Dist: sphinx ; extra == 'docs'
Requires-Dist: sphinx-rtd-theme ; extra == 'docs'
Requires-Dist: sphinxcontrib-katex ; extra == 'docs'
Provides-Extra: examples
Requires-Dist: matplotlib ; extra == 'examples'
Provides-Extra: other
Requires-Dist: xlrd ; extra == 'other'
Requires-Dist: pandas ; extra == 'other'
Requires-Dist: seaborn ; extra == 'other'
Requires-Dist: imageio ; extra == 'other'
Provides-Extra: tests
Requires-Dist: pytest ; extra == 'tests'
